spooq/__init__.py
spooq/_version.py
spooq/shared.py
spooq/spooq_logger.py
spooq/extractor/__init__.py
spooq/extractor/extractor.py
spooq/extractor/jdbc.py
spooq/extractor/json_files.py
spooq/extractor/tools.py
spooq/loader/__init__.py
spooq/loader/hive_loader.py
spooq/loader/loader.py
spooq/pipeline/__init__.py
spooq/pipeline/factory.py
spooq/pipeline/pipeline.py
spooq/transformer/__init__.py
spooq/transformer/annotator.py
spooq/transformer/base_cleaner.py
spooq/transformer/enum_cleaner.py
spooq/transformer/exploder.py
spooq/transformer/mapper.py
spooq/transformer/mapper_transformations.py
spooq/transformer/newest_by_group.py
spooq/transformer/null_cleaner.py
spooq/transformer/sieve.py
spooq/transformer/threshold_cleaner.py
spooq/transformer/transformer.py
spooq-4.0.1.dist-info/licenses/AUTHORS.rst
spooq-4.0.1.dist-info/licenses/LICENSE
spooq-4.0.1.dist-info/METADATA
spooq-4.0.1.dist-info/WHEEL
spooq-4.0.1.dist-info/top_level.txt
spooq-4.0.1.dist-info/RECORD
