Metadata-Version: 2.4
Name: Spooq
Version: 4.0.1
Summary: Spooq is a PySpark based helper library for ETL data ingestion pipeline in Data Lakes.
Home-page: https://github.com/Breaka84/Spooq
Author: David Hohensinn
Author-email: breaka@gmx.at
Project-URL: Documentation, https://spooq.readthedocs.io
Keywords: spooq,spark,hive,cloudera,hadoop,etl,data ingestion,data wrangling,databricks,big data,batch,streaming,data engineering
Classifier: Development Status :: 5 - Production/Stable
Classifier: Intended Audience :: Developers
Classifier: Natural Language :: English
Classifier: Programming Language :: Python :: 3.8
License-File: LICENSE
License-File: AUTHORS.rst
Requires-Dist: pandas
Requires-Dist: future
Requires-Dist: requests
Dynamic: author
Dynamic: author-email
Dynamic: classifier
Dynamic: description
Dynamic: home-page
Dynamic: keywords
Dynamic: license-file
Dynamic: project-url
Dynamic: requires-dist
Dynamic: summary
